odoo10_addon_web_tree_dynamic_colored_field-10.0.1.0.0-py2.7-nspkg.pth
odoo/addons/web_tree_dynamic_colored_field/README.rst
odoo/addons/web_tree_dynamic_colored_field/__init__.py
odoo/addons/web_tree_dynamic_colored_field/__manifest__.py
odoo/addons/web_tree_dynamic_colored_field/demo/res_users.xml
odoo/addons/web_tree_dynamic_colored_field/i18n/es.po
odoo/addons/web_tree_dynamic_colored_field/i18n/fi.po
odoo/addons/web_tree_dynamic_colored_field/i18n/sl.po
odoo/addons/web_tree_dynamic_colored_field/static/description/icon.png
odoo/addons/web_tree_dynamic_colored_field/static/src/js/web_tree_dynamic_colored_field.js
odoo/addons/web_tree_dynamic_colored_field/static/src/xml/web_tree_dynamic_colored_field.xml
odoo/addons/web_tree_dynamic_colored_field/views/web_tree_dynamic_colored_field.xml
odoo10_addon_web_tree_dynamic_colored_field-10.0.1.0.0.dist-info/DESCRIPTION.rst
odoo10_addon_web_tree_dynamic_colored_field-10.0.1.0.0.dist-info/METADATA
odoo10_addon_web_tree_dynamic_colored_field-10.0.1.0.0.dist-info/RECORD
odoo10_addon_web_tree_dynamic_colored_field-10.0.1.0.0.dist-info/WHEEL
odoo10_addon_web_tree_dynamic_colored_field-10.0.1.0.0.dist-info/metadata.json
odoo10_addon_web_tree_dynamic_colored_field-10.0.1.0.0.dist-info/namespace_packages.txt
odoo10_addon_web_tree_dynamic_colored_field-10.0.1.0.0.dist-info/top_level.txt
